dres/__init__.py
dres/aes.py
dres/cipher.py
dres/exceptions.py
dres/key_exchange.py
dres/resources.py
dres/util.py
dres-0.2.0.dist-info/licenses/LICENSE
dres-0.2.0.dist-info/METADATA
dres-0.2.0.dist-info/WHEEL
dres-0.2.0.dist-info/top_level.txt
dres-0.2.0.dist-info/RECORD
